gistdawater/__init__.py
gistdawater/mainfile.py
gistdawater-0.0.6.dist-info/LICENSE
gistdawater-0.0.6.dist-info/LICENSE.txt
gistdawater-0.0.6.dist-info/METADATA
gistdawater-0.0.6.dist-info/WHEEL
gistdawater-0.0.6.dist-info/top_level.txt
gistdawater-0.0.6.dist-info/RECORD
