Metadata-Version: 2.1
Name: gistdawater
Version: 0.0.6
Summary: Waterdetection for landsat8
Author: Gistda
Author-email: gistdathailand@gmail.com
License: MIT
Keywords: geo,oepn data cube,earth
Classifier: Development Status :: 1 - Planning
Classifier: Intended Audience :: Education
Classifier: Topic :: Software Development :: Build Tools
Classifier: License :: OSI Approved :: MIT License
Classifier: Programming Language :: Python :: 3.8
License-File: LICENSE
License-File: LICENSE.txt
Requires-Dist: numpy
Requires-Dist: matplotlib
